MANIFEST.in
README.rst
setup.py
paquete/__init__.py
paquete/main.py
paquete/modulo1.py
paquete/operaciones.py
paquete.egg-info/PKG-INFO
paquete.egg-info/SOURCES.txt
paquete.egg-info/dependency_links.txt
paquete.egg-info/not-zip-safe
paquete.egg-info/requires.txt
paquete.egg-info/top_level.txt